COPYING
COPYING.LESSER
MANIFEST.in
README.md
setup.cfg
setup.py
bioLEC/LEC.py
bioLEC/__init__.py
bioLEC/documentation.py
bioLEC.egg-info/PKG-INFO
bioLEC.egg-info/SOURCES.txt
bioLEC.egg-info/dependency_links.txt
bioLEC.egg-info/requires.txt
bioLEC.egg-info/top_level.txt
bioLEC/Notebooks/dataset/.DS_Store
bioLEC/Notebooks/dataset/dem.csv
bioLEC/Notebooks/dataset/kosciuszko.csv
bioLEC/Notebooks/images/.DS_Store
bioLEC/Notebooks/images/LECres.jpg
bioLEC/Notebooks/images/binder.jpg
bioLEC/Notebooks/images/boundcond.jpg
bioLEC/Notebooks/images/fig1.png
bioLEC/Notebooks/images/fig3.jpg
bioLEC/Notebooks/images/fitness.jpg
bioLEC/Notebooks/images/graph.jpg
bioLEC/Notebooks/images/intro.jpg
bioLEC/Notebooks/images/kosinit.jpg
bioLEC/Notebooks/images/kosres.jpg
bioLEC/Notebooks/images/parallel.jpg
bioLEC/Notebooks/images/path.jpg
bioLEC/Notebooks/images/pearson.jpg
bioLEC/Notebooks/notebooks/bioLEC1-genericCase.ipynb
bioLEC/Notebooks/notebooks/bioLEC2-Kosciuszko.ipynb
bioLEC/Notebooks/notebooks/bioLEC3-MeshGen.ipynb
bioLEC/Notebooks/notebooks/runLEC.py