Metadata-Version: 2.1
Name: bioLEC
Version: 1.0.0
Summary: A Python interface to compute biodiversity metric based on landscape elevational connectivity.
Home-page: https://github.com/Geodels/bioLEC
Author: Tristan Salles
Author-email: tristan.salles@sydney.edu.au
License: UNKNOWN
Platform: UNKNOWN
Classifier: Programming Language :: Python :: 2
Classifier: Programming Language :: Python :: 2.6
Classifier: Programming Language :: Python :: 2.7
Classifier: Programming Language :: Python :: 3
Classifier: Programming Language :: Python :: 3.3
Classifier: Programming Language :: Python :: 3.4
Classifier: Programming Language :: Python :: 3.5
Classifier: Programming Language :: Python :: 3.6
Requires-Python: >=2.7, >=3.5
